Metadata-Version: 1.1
Name: pyparis
Version: 0.0.1
Summary: Multi-scale modularity based clustering algorithm
Home-page: https://github.com/Charpenb/paris
Author: Bertrand Charpentier
Author-email: bercha@kth.se
License: Apache License 2.0
Keywords: modularity multi-scale hierarchical graph clustering
Platform: UNKNOWN
Classifier: Topic :: System :: Clustering
